ft_package_obrittne/__init__.py
ft_package_obrittne/functions.py
ft_package_obrittne-0.0.1.dist-info/LICENSE
ft_package_obrittne-0.0.1.dist-info/METADATA
ft_package_obrittne-0.0.1.dist-info/WHEEL
ft_package_obrittne-0.0.1.dist-info/top_level.txt
ft_package_obrittne-0.0.1.dist-info/RECORD
