Metadata-Version: 2.1
Name: ft_package_obrittne
Version: 0.0.1
Summary: Best package
Author: obrittne
Author-email: obrittne.email@example.com
Classifier: Programming Language :: Python :: 3
Classifier: License :: OSI Approved :: MIT License
Classifier: Operating System :: OS Independent
Requires-Python: >=3.6
License-File: LICENSE
